mofstructure/__init__.py
mofstructure/cof_stacking.py
mofstructure/db/iupacname.msgpack
mofstructure/filetyper.py
mofstructure/mofdeconstructor.py
mofstructure/obsolate/buildingunits.py
mofstructure/obsolate/collect_building_units.py
mofstructure/obsolate/collect_data.py
mofstructure/obsolate/collect_oms.py
mofstructure/obsolate/collect_porosity.py
mofstructure/porosity.py
mofstructure/scripts/__init__.py
mofstructure/scripts/buildingunits.py
mofstructure/scripts/collect_building_units.py
mofstructure/scripts/collect_data.py
mofstructure/scripts/collect_oms.py
mofstructure/scripts/collect_porosity.py
mofstructure/scripts/curate_structures.py
mofstructure/structure.py
mofstructure-0.1.8.4.dist-info/METADATA
mofstructure-0.1.8.4.dist-info/WHEEL
mofstructure-0.1.8.4.dist-info/entry_points.txt
mofstructure-0.1.8.4.dist-info/licenses/LICENSE
mofstructure-0.1.8.4.dist-info/RECORD
