Metadata-Version: 2.4
Name: mofstructure
Version: 0.1.8.4
Summary: A Python tool to deconstruct MOFs into building units and compute porosity. The code removes guests from MOFs and all porous systems, computes SMILES strings and InChIKeys of all building units.
License: MIT
License-File: LICENSE
Keywords: guest removal,InChIKeys,InChI,SMILES,PLD,LCD,MOF,COF,zeolites,accessible surface area,void fraction,coordination number,porosity,zeo++,SBU,point of extension
Author: Dinga Wonanke
Author-email: bafgreat@gmail.com
Requires-Python: >=3.9,<4.0
Classifier: License :: OSI Approved :: MIT License
Classifier: Programming Language :: Python :: 3
Classifier: Programming Language :: Python :: 3.9
Classifier: Programming Language :: Python :: 3.10
Classifier: Programming Language :: Python :: 3.11
Classifier: Programming Language :: Python :: 3.12
Classifier: Programming Language :: Python :: 3.13
Classifier: Programming Language :: Python :: 3.14
Provides-Extra: rdkit
Requires-Dist: ase (>=3.19.0)
Requires-Dist: msgpack (>=1.1.0,<2.0.0)
Requires-Dist: networkx (>=2.6.3)
Requires-Dist: omsdetector-forked (>=2026.1.6,<2027.0.0)
Requires-Dist: openbabel-wheel (==3.1.1.22)
Requires-Dist: pandas (>=1.3.5)
Requires-Dist: pyzeo (>=0.1.1)
Requires-Dist: rdkit (>=2022.9.5) ; extra == "rdkit"
